orgtemp/__init__.py
orgtemp/__main__.py
orgtemp/install.py
orgtemp/sources.py
org_template_builder-0.1.2.dist-info/LICENSE
org_template_builder-0.1.2.dist-info/WHEEL
org_template_builder-0.1.2.dist-info/METADATA
org_template_builder-0.1.2.dist-info/RECORD
