Metadata-Version: 2.1
Name: org-template-builder
Version: 0.1.2
Summary: Python Org-Mode Template Builder.
License: MIT
Author: AlbertoV5
Author-email: 58243333+AlbertoV5@users.noreply.github.com
Requires-Python: >=3.7,<4.0
Classifier: License :: OSI Approved :: MIT License
Classifier: Programming Language :: Python :: 3
Classifier: Programming Language :: Python :: 3.7
Classifier: Programming Language :: Python :: 3.8
Classifier: Programming Language :: Python :: 3.9
Classifier: Programming Language :: Python :: 3.10
Requires-Dist: bs4 (>=0.0.1,<0.0.2)
Requires-Dist: orgparse (>=0.3.1,<0.4.0)
Requires-Dist: requests (==2.28.1)
Requires-Dist: selenium (>=4.4.3,<5.0.0)
Requires-Dist: webdriver-manager (>=3.8.3,<4.0.0)
